video_upscaler/__init__.py
video_upscaler/video_upscaler.py
video_upscaler-0.2.0.dist-info/LICENSE.txt
video_upscaler-0.2.0.dist-info/METADATA
video_upscaler-0.2.0.dist-info/WHEEL
video_upscaler-0.2.0.dist-info/top_level.txt
video_upscaler-0.2.0.dist-info/RECORD
