Metadata-Version: 2.1
Name: video_upscaler
Version: 0.2.0
Summary: A package for resizing videos using Automatic1111 web UI
Home-page: https://github.com/Yalton/video_upscaler
Author: Dalton Bailey
Author-email: drbailey117@example.com
Classifier: Development Status :: 3 - Alpha
Classifier: Intended Audience :: Developers
Classifier: License :: OSI Approved :: MIT License
Classifier: Programming Language :: Python :: 3
Classifier: Programming Language :: Python :: 3.6
Classifier: Programming Language :: Python :: 3.7
Classifier: Programming Language :: Python :: 3.8
Classifier: Programming Language :: Python :: 3.9
License-File: LICENSE.txt
Requires-Dist: ffmpeg-python
Requires-Dist: Pillow
Requires-Dist: webuiapi
